matzip/__init__.py
matzip/matzip.py
matzip-0.0.1.dist-info/DESCRIPTION.rst
matzip-0.0.1.dist-info/METADATA
matzip-0.0.1.dist-info/RECORD
matzip-0.0.1.dist-info/WHEEL
matzip-0.0.1.dist-info/metadata.json
matzip-0.0.1.dist-info/top_level.txt
matzip-0.0.1.dist-info/zip-safe
